{
    "name": "Billyy Kneeling Handjob 2 Front",
    "modpack": "BillyyAnimations",
    "length": 2,
    "navigations": [
        {
            "destination": "BillyyHj2-3",
            "description": "Next",
            "icon": "OStim/symbols/arrow_right"
        },
        {
            "destination": "BillyyHj2-1",
            "description": "Back",
            "icon": "OStim/symbols/arrow_left"
        },
        {
            "destination": "BillyysHumanPage2",
            "description": "Return",
            "icon": "OStim/symbols/return"
        }
    ],
    "speeds": [
        {
            "animation": "BillyyHj2_2"
        }
    ],
    "actors": [
        {
            "intendedSex": "male",
            "sosBend": 1,
            "scale": 1,
            "feetOnGround": true,
            "tags": [
                "standing"
            ]
        },
        {
            "intendedSex": "female",
            "scale": 1,
            "feetOnGround": false,
            "tags": [
                "kneeling"
            ]
        }
    ],
    "actions": [
        {
            "type": "handjob",
            "actor": 1,
            "target": 0
        }
    ],
    "tags": [
        "billyy"
    ]
}