{
    "name": "Billyy Lesbian Cunnilingus 5 Missionary",
    "modpack": "BillyyAnimations",
    "length": 2,
    "navigations": [
        {
            "destination": "BillyyLcunn5-3SwappedM0-F1",
            "description": "Next",
            "icon": "OStim/symbols/next"
        },
        {
            "destination": "BillyyLcunn5-1SwappedM0-F1",
            "description": "Back",
            "icon": "OStim/symbols/previous"
        },
        {
            "destination": "BillyysLesbianPage1",
            "description": "Return",
            "icon": "OStim/symbols/return"
        },
        {
            "destination": "BillyyLcunn5-2",
            "description": "Rotate females",
            "icon": "OStim/symbols/rotate_cw"
        }
    ],
    "speeds": [
        {
            "animation": "BillyyLcunn5_2"
        }
    ],
    "actors": [
        {
            "intendedSex": "female",
            "scale": 1,
            "feetOnGround": false,
            "tags": [
                "allfours"
            ],
            "animationIndex": 1
        },
        {
            "intendedSex": "female",
            "scale": 1,
            "feetOnGround": true,
            "tags": [
                "lyingback"
            ],
            "animationIndex": 0
        }
    ],
    "actions": [
        {
            "type": "lickingvagina",
            "actor": 1,
            "target": 0
        },
        {
            "type": "pattinghead",
            "actor": 0,
            "target": 1
        }
    ],
    "tags": [
        "billyy"
    ]
}