{
    "name": "Billyy Laying Nelson",
    "modpack": "BillyyAnimations",
    "length": 8.333333,
    "destination": "BillyyNellay-4",
    "speeds": [
        {
            "animation": "BillyyNellay_5"
        }
    ],
    "actors": [
        {
            "intendedSex": "male",
            "sosBend": 9,
            "scale": 1,
            "feetOnGround": true,
            "tags": [
                "lyingback",
                "onbottom",
                "climaxing"
            ]
        },
        {
            "intendedSex": "female",
            "scale": 1,
            "feetOnGround": false,
            "tags": [
                "lyingback",
                "facingaway",
                "ontop",
                "climaxing"
            ]
        }
    ],
    "actions": [
        {
            "type": "vaginalsex",
            "actor": 0,
            "target": 1
        },
        {
            "type": "holdinghead",
            "actor": 0,
            "target": 1
        }
    ],
    "tags": [
        "billyy",
        "transition"
    ]
}